[
    /* 1 */
    {
        "_id" : "59824bab10983369be8285eb",
        "group" : "Air",
        "type" : "Plane",
        "model" : "F-22"
    },

    /* 2 */
    {
        "_id" : "59824bb710983369be8285ec",
        "group" : "Air",
        "type" : "Plane",
        "model" : "F-22"
    },

    /* 3 */
    {
        "_id" : "59824bbf10983369be8285ed",
        "group" : "Air",
        "type" : "Plane",
        "model" : "Sukhoi"
    },

    /* 4 */
    {
        "_id" : "59824bc710983369be8285ee",
        "group" : "Air",
        "type" : "Plane",
        "model" : "MiG"
    },

    /* 5 */
    {
        "_id" : "59824bd010983369be8285ef",
        "group" : "Air",
        "type" : "Helicopter",
        "model" : "Apache"
    },

    /* 6 */
    {
        "_id" : "59824bd810983369be8285f0",
        "group" : "Air",
        "type" : "Helicopter",
        "model" : "Kamov"
    },

    /* 7 */
    {
        "_id" : "59824be010983369be8285f1",
        "group" : "Sea",
        "type" : "Boat",
        "model" : "Sailboat"
    },

    /* 8 */
    {
        "_id" : "59824be510983369be8285f2",
        "group" : "Sea",
        "type" : "Boat",
        "model" : "Jetboat"
    },

    /* 9 */
    {
        "_id" : "59824beb10983369be8285f3",
        "group" : "Sea",
        "type" : "Submarine",
        "model" : "Standard"
    },

    /* 10 */
    {
        "_id" : "59824bf210983369be8285f4",
        "group" : "Land",
        "type" : "Car",
        "model" : "Camaro"
    },

    /* 11 */
    {
        "_id" : "59824bf910983369be8285f5",
        "group" : "Land",
        "type" : "Car",
        "model" : "AMG GT R"
    },

    /* 12 */
    {
        "_id" : "59824bff10983369be8285f6",
        "group" : "Land",
        "type" : "Car",
        "model" : "Lamborghini"
    },

    /* 13 */
    {
        "_id" : "59824c0610983369be8285f7",
        "group" : "Land",
        "type" : "Truck",
        "model" : "Unimog"
    },

    /* 14 */
    {
        "_id" : "59824c0c10983369be8285f8",
        "group" : "Land",
        "type" : "Truck",
        "model" : "Western Star 5700"
    }
]